invoice_parser/__init__.py
invoice_parser/_modidx.py
invoice_parser/app.py
invoice_parser/core.py
invoice_parser/imports.py
invoice_parser/utils.py
invoice_parser/api/__init__.py
invoice_parser/api/app.py
invoice_parser/api/imports.py
invoice_parser/api/utils.py
invoice_parser-0.0.6.dist-info/LICENSE
invoice_parser-0.0.6.dist-info/METADATA
invoice_parser-0.0.6.dist-info/WHEEL
invoice_parser-0.0.6.dist-info/entry_points.txt
invoice_parser-0.0.6.dist-info/top_level.txt
invoice_parser-0.0.6.dist-info/RECORD
