Metadata-Version: 2.1
Name: invoice-parser
Version: 0.0.6
Summary: Tools for parsing and extracting information from invoices.
Home-page: https://github.com/HamzaFarhan/invoice_parser
Author: Hamza Farhan
Author-email: thehamza96@gmail.com
License: Apache Software License 2.0
Keywords: nbdev jupyter notebook python
Classifier: Development Status :: 4 - Beta
Classifier: Intended Audience :: Developers
Classifier: Natural Language :: English
Classifier: Programming Language :: Python :: 3.7
Classifier: Programming Language :: Python :: 3.8
Classifier: Programming Language :: Python :: 3.9
Classifier: Programming Language :: Python :: 3.10
Classifier: License :: OSI Approved :: Apache Software License
Requires-Python: >=3.7
License-File: LICENSE
Requires-Dist: dreamai
Requires-Dist: langchain-ray
Requires-Dist: pdfplumber
Requires-Dist: pypdf
Requires-Dist: einops
Provides-Extra: dev
